conductor/ConductorWorker.py
conductor/__init__.py
conductor/conductor.py
conductor_copy-1.0.0.dist-info/METADATA
conductor_copy-1.0.0.dist-info/WHEEL
conductor_copy-1.0.0.dist-info/top_level.txt
conductor_copy-1.0.0.dist-info/RECORD
